xmlwitch.py
xmlwitch-0.3.dist-info/DESCRIPTION.rst
xmlwitch-0.3.dist-info/METADATA
xmlwitch-0.3.dist-info/RECORD
xmlwitch-0.3.dist-info/WHEEL
xmlwitch-0.3.dist-info/metadata.json
xmlwitch-0.3.dist-info/top_level.txt
