Metadata-Version: 2.0
Name: xmlwitch
Version: 0.3
Summary: xmlwitch offers Pythonic XML generation through context generators
Home-page: http://github.com/galvez/xmlwitch/
Author: Jonas Galvez
Author-email: jonasgalvez@gmail.com
License: BSD
Platform: Python 2.5 and later
Classifier: Intended Audience :: Developers
Classifier: Development Status :: 5 - Production/Stable
Classifier: License :: OSI Approved :: BSD License
Classifier: Operating System :: OS Independent
Classifier: Programming Language :: Python
Classifier: Topic :: Software Development :: Libraries
Classifier: Topic :: Text Processing :: Markup :: HTML
Classifier: Topic :: Text Processing :: Markup :: XML
